fastn/__init__.py
fastn/server.py
fastn_server-0.1.0.dist-info/METADATA
fastn_server-0.1.0.dist-info/WHEEL
fastn_server-0.1.0.dist-info/entry_points.txt
fastn_server-0.1.0.dist-info/licenses/LICENSE
fastn_server-0.1.0.dist-info/RECORD
