Metadata-Version: 2.4
Name: fastn-server
Version: 0.1.0
Summary: A FastN MCP server for executing FastN tools
Project-URL: Homepage, https://fastn.ai
Project-URL: Repository, https://github.com/fastn/fastn-server-package
Author: FastN Team
License: MIT License
License-File: LICENSE
Classifier: Development Status :: 4 - Beta
Classifier: Environment :: Console
Classifier: Intended Audience :: Developers
Classifier: Programming Language :: Python :: 3
Classifier: Programming Language :: Python :: 3.10
Classifier: Programming Language :: Python :: 3.11
Classifier: Programming Language :: Python :: 3.12
Requires-Python: >=3.10
Requires-Dist: httpx>=0.28.1
Requires-Dist: mcp[cli]>=1.2.0
